README.md
setup.py
xpan/__init__.py
xpan/api_client.py
xpan/configuration.py
xpan/exceptions.py
xpan/model_utils.py
xpan/rest.py
xpan.egg-info/PKG-INFO
xpan.egg-info/SOURCES.txt
xpan.egg-info/dependency_links.txt
xpan.egg-info/requires.txt
xpan.egg-info/top_level.txt
xpan/api/__init__.py
xpan/api/auth_api.py
xpan/api/fileinfo_api.py
xpan/api/filemanager_api.py
xpan/api/fileupload_api.py
xpan/api/multimediafile_api.py
xpan/api/userinfo_api.py
xpan/model/__init__.py
xpan/model/oauth_token_authorization_code_response.py
xpan/model/oauth_token_device_code_response.py
xpan/model/oauth_token_device_token_response.py
xpan/model/oauth_token_refresh_token_response.py
xpan/model/quotaresponse.py
xpan/model/uinforesponse.py