Metadata-Version: 2.1
Name: xpan
Version: 0.0.1
Summary: An API library for BaiduNetdisk
Keywords: BaiduNetdisk,openapi_client
Requires-Python: >=3.6
